odoo/addons/website_sale_category_breadcrumb/README.rst
odoo/addons/website_sale_category_breadcrumb/__init__.py
odoo/addons/website_sale_category_breadcrumb/__manifest__.py
odoo/addons/website_sale_category_breadcrumb/i18n/es.po
odoo/addons/website_sale_category_breadcrumb/i18n/it.po
odoo/addons/website_sale_category_breadcrumb/i18n/website_sale_category_breadcrumb.pot
odoo/addons/website_sale_category_breadcrumb/readme/CONTRIBUTORS.rst
odoo/addons/website_sale_category_breadcrumb/readme/DESCRIPTION.rst
odoo/addons/website_sale_category_breadcrumb/readme/USAGE.rst
odoo/addons/website_sale_category_breadcrumb/static/description/icon.png
odoo/addons/website_sale_category_breadcrumb/static/description/index.html
odoo/addons/website_sale_category_breadcrumb/views/templates.xml
odoo_addon_website_sale_category_breadcrumb-16.0.1.0.0.2.dist-info/METADATA
odoo_addon_website_sale_category_breadcrumb-16.0.1.0.0.2.dist-info/WHEEL
odoo_addon_website_sale_category_breadcrumb-16.0.1.0.0.2.dist-info/top_level.txt
odoo_addon_website_sale_category_breadcrumb-16.0.1.0.0.2.dist-info/RECORD
